setup.py
WorkFlow_HS_Utils.egg-info/PKG-INFO
WorkFlow_HS_Utils.egg-info/SOURCES.txt
WorkFlow_HS_Utils.egg-info/dependency_links.txt
WorkFlow_HS_Utils.egg-info/requires.txt
WorkFlow_HS_Utils.egg-info/top_level.txt
Workflow_HS/__init__.py