Metadata-Version: 2.1
Name: WorkFlow-HS-Utils
Version: 0.1.0
Summary: Allen.huang's private utils
Home-page: https://hs-personproject.coding.net/p/ttt/d/workflow/git
Author: Allen.huang
Author-email: fengyeyoni@163.com
License: MIT Licence
Keywords: pip,WorkFlow_HS_Utils
Platform: any
